pysettings_manager/__init__.py
pysettings_manager/config_file_exists.py
pysettings_manager/load.py
pysettings_manager/save.py
pysettings_manager-1.0.0.dist-info/LICENSE
pysettings_manager-1.0.0.dist-info/METADATA
pysettings_manager-1.0.0.dist-info/WHEEL
pysettings_manager-1.0.0.dist-info/top_level.txt
pysettings_manager-1.0.0.dist-info/RECORD
