Metadata-Version: 2.1
Name: pysettings-manager
Version: 1.0.0
Summary: A python module for saving and loading settings
Project-URL: Homepage, https://github.com/sryu1/pysettings-manager
Project-URL: Bug Tracker, https://github.com/sryu1/pysettings-manager/issues
Project-URL: Documentation, https://sryu1.gitbook.io/pysettings-manager
Classifier: Programming Language :: Python
Classifier: Programming Language :: Python :: 3
Classifier: Programming Language :: Python :: 3.7
Classifier: Programming Language :: Python :: 3.8
Classifier: Programming Language :: Python :: 3.9
Classifier: Programming Language :: Python :: 3.10
Classifier: Programming Language :: Python :: 3.11
Requires-Python: >=3.7
License-File: LICENSE
